awkward_pandas/__init__.py
awkward_pandas/accessor.py
awkward_pandas/array.py
awkward_pandas/dtype.py
awkward_pandas/io.py
awkward_pandas/lib.py
awkward_pandas/py.typed
awkward_pandas/strings.py
awkward_pandas/version.py
awkward_pandas-2022.12a1.dist-info/METADATA
awkward_pandas-2022.12a1.dist-info/WHEEL
awkward_pandas-2022.12a1.dist-info/licenses/LICENSE
awkward_pandas-2022.12a1.dist-info/RECORD
